macroni/__init__.py
macroni/cli.py
macroni/interpreter/__init__.py
macroni/interpreter/grammar.py
macroni/interpreter/macroni_debugger.py
macroni/interpreter/macroni_interpret.py
macroni/interpreter/types.py
macroni/util/__init__.py
macroni/util/input_handler.py
macroni/util/mouse_utils.py
macroni/util/ocr.py
macroni/util/output_handler.py
macroni/util/template_match.py
macroni/util/vision.py
macroni-0.2.3.dist-info/licenses/LICENSE.txt
macroni-0.2.3.dist-info/METADATA
macroni-0.2.3.dist-info/WHEEL
macroni-0.2.3.dist-info/entry_points.txt
macroni-0.2.3.dist-info/top_level.txt
macroni-0.2.3.dist-info/RECORD
