Metadata-Version: 2.4
Name: macroni
Version: 0.2.3
Summary: Macroni interpreter
Author: Sam Schreiber
Project-URL: Homepage, https://github.com/srschreiber/macroni
Project-URL: Issues, https://github.com/srschreiber/macroni/issues
Keywords: dsl,automation,macro,opencv,ocr,macroni
Classifier: Programming Language :: Python :: 3
Classifier: Programming Language :: Python :: 3.12
Classifier: License :: OSI Approved :: MIT License
Classifier: Operating System :: MacOS
Classifier: Operating System :: Microsoft :: Windows
Classifier: Operating System :: POSIX :: Linux
Requires-Python: <3.13,>=3.12
License-File: LICENSE.txt
Requires-Dist: click>=8.3
Requires-Dist: easyocr>=1.7.2
Requires-Dist: lark>=1.3.1
Requires-Dist: mss>=10.1.0
Requires-Dist: opencv-python>=4.12.0.88
Requires-Dist: pillow>=12.0.0
Requires-Dist: pyautogui>=0.9.54
Requires-Dist: pyscreeze>=1.0.1
Requires-Dist: pynput>=1.8.1
Requires-Dist: pyreadline3>=3.5.4
Dynamic: license-file
